file_manager_spw2/__init__.py
file_manager_spw2-0.2.dist-info/licenses/LICENSE
file_manager_spw2-0.2.dist-info/METADATA
file_manager_spw2-0.2.dist-info/WHEEL
file_manager_spw2-0.2.dist-info/top_level.txt
file_manager_spw2-0.2.dist-info/RECORD
