Metadata-Version: 2.4
Name: file_manager_spw2
Version: 0.2
Summary: un tipo de gestor de archivos
Home-page: https://github.com/Mrreich/file_manager_reichtangle
Download-URL: https://github.com/Mrreich/file_manager_reichtangle/releases/tag/v0.1
Author: spw2
Author-email: mr.reich.oficial.1@gmail.com
License: MIT
Keywords: testing,logging,example
License-File: LICENSE
Dynamic: author
Dynamic: author-email
Dynamic: description
Dynamic: description-content-type
Dynamic: download-url
Dynamic: home-page
Dynamic: keywords
Dynamic: license
Dynamic: license-file
Dynamic: summary
